{
  "id": "1.14.3-pre3",
  "type": "snapshot",
  "url": "https://launchermeta.mojang.com/v1/packages/767d65ec7037b0b46300e720fd3f2bf56afad1c6/1.14.3-pre3.json",
  "time": "2019-08-22T12:46:36+00:00",
  "releaseTime": "2019-06-14T08:03:33+00:00",
  "client": "https://launcher.mojang.com/v1/objects/360c54d41522541f6eb303771192433de4ea1235/client.jar",
  "server": "https://launcher.mojang.com/v1/objects/a46e49e1541cf24a75aabe2756514565de83634a/server.jar",
  "registries": [
    "activity",
    "advancement",
    "biome",
    "biome_source_type",
    "block",
    "block_entity_type",
    "carver",
    "chunk_generator_type",
    "chunk_status",
    "command",
    "custom_stat",
    "decorator",
    "dimension_type",
    "enchantment",
    "entity_type",
    "feature",
    "fluid",
    "item",
    "loot_table",
    "memory_module_type",
    "menu",
    "mob_effect",
    "motive",
    "particle_type",
    "point_of_interest_type",
    "potion",
    "recipe",
    "recipe_serializer",
    "recipe_type",
    "rule_test",
    "schedule",
    "sensor_type",
    "sound_event",
    "stat_type",
    "structure_feature",
    "structure_piece",
    "structure_pool_element",
    "structure_processor",
    "surface_builder",
    "tag",
    "villager_profession",
    "villager_type"
  ],
  "reports": [
    "blocks",
    "commands",
    "registries"
  ]
}